[
  {
    "hints": [
      "Sujeto: el desarrollador backend",
      "Verbo: optimizar",
      "Complemento: la velocidad del servidor"
    ],
    "hintDisplay": "Sujeto: el desarrollador backend / Verbo: optimizar / Complemento: la velocidad del servidor",
    "spanishSentence": "El desarrollador backend optimiza la velocidad del servidor",
    "correctSentence": "The backend developer optimizes the server speed",
    "cards": [
      {
        "id": "c1",
        "text": "The",
        "isDistractor": false
      },
      {
        "id": "c2",
        "text": "backend",
        "isDistractor": false
      },
      {
        "id": "c3",
        "text": "developer",
        "isDistractor": false
      },
      {
        "id": "c4",
        "text": "optimizes",
        "isDistractor": false
      },
      {
        "id": "c5",
        "text": "the",
        "isDistractor": false
      },
      {
        "id": "c6",
        "text": "server",
        "isDistractor": false
      },
      {
        "id": "c7",
        "text": "speed",
        "isDistractor": false
      },
      {
        "id": "d1",
        "text": "improves",
        "isDistractor": true
      },
      {
        "id": "d2",
        "text": "frontend",
        "isDistractor": true
      },
      {
        "id": "d3",
        "text": "efficiency",
        "isDistractor": true
      }
    ],
    "translations": {
      "the": "el/la",
      "backend": "backend",
      "developer": "desarrollador",
      "optimizes": "optimiza",
      "server": "servidor",
      "speed": "velocidad",
      "improves": "mejora",
      "frontend": "frontend",
      "efficiency": "eficiencia"
    },
    "metadata": {
      "tense": "present simple",
      "isNegative": false,
      "isQuestion": false,
      "difficulty": "beginner",
      "topic": "software engineering"
    }
  },
  {
    "hints": [
      "Sujeto: el equipo (the team)",
      "Verbo: configurar (to set up/configure)",
      "Complemento: la pipeline de CI (the CI pipeline)"
    ],
    "hintDisplay": "Sujeto: el equipo / Verbo: configurar / Complemento: la pipeline de CI",
    "spanishSentence": "El equipo configura la pipeline de CI cada semana",
    "correctSentence": "The team configures the CI pipeline every week",
    "cards": [
      {
        "id": "c1",
        "text": "The",
        "isDistractor": false
      },
      {
        "id": "c2",
        "text": "team",
        "isDistractor": false
      },
      {
        "id": "c3",
        "text": "configures",
        "isDistractor": false
      },
      {
        "id": "c4",
        "text": "the",
        "isDistractor": false
      },
      {
        "id": "c5",
        "text": "CI",
        "isDistractor": false
      },
      {
        "id": "c6",
        "text": "pipeline",
        "isDistractor": false
      },
      {
        "id": "c7",
        "text": "every",
        "isDistractor": false
      },
      {
        "id": "c8",
        "text": "week",
        "isDistractor": false
      },
      {
        "id": "d1",
        "text": "configure",
        "isDistractor": true
      },
      {
        "id": "d2",
        "text": "develops",
        "isDistractor": true
      },
      {
        "id": "d3",
        "text": "month",
        "isDistractor": true
      }
    ],
    "translations": {
      "the": "el/la",
      "team": "equipo",
      "configures": "configura",
      "ci": "CI",
      "pipeline": "pipeline",
      "every": "cada",
      "week": "semana",
      "configure": "configurar",
      "develops": "desarrolla",
      "month": "mes"
    },
    "metadata": {
      "tense": "present simple",
      "isNegative": false,
      "isQuestion": false,
      "difficulty": "beginner",
      "topic": "software engineering"
    }
  },
  {
    "hints": [
      "Sujeto: el desarrollador backend",
      "Verbo: migrar",
      "Complemento: la base de datos a un nuevo servidor"
    ],
    "hintDisplay": "Sujeto: el desarrollador backend / Verbo: migrar / Complemento: la base de datos a un nuevo servidor",
    "spanishSentence": "El desarrollador backend migra la base de datos a un nuevo servidor.",
    "correctSentence": "The backend developer migrates the database to a new server.",
    "cards": [
      {
        "id": "c1",
        "text": "The",
        "isDistractor": false
      },
      {
        "id": "c2",
        "text": "backend",
        "isDistractor": false
      },
      {
        "id": "c3",
        "text": "developer",
        "isDistractor": false
      },
      {
        "id": "c4",
        "text": "migrates",
        "isDistractor": false
      },
      {
        "id": "c5",
        "text": "the",
        "isDistractor": false
      },
      {
        "id": "c6",
        "text": "database",
        "isDistractor": false
      },
      {
        "id": "c7",
        "text": "to",
        "isDistractor": false
      },
      {
        "id": "c8",
        "text": "a",
        "isDistractor": false
      },
      {
        "id": "c9",
        "text": "new",
        "isDistractor": false
      },
      {
        "id": "c10",
        "text": "server",
        "isDistractor": false
      },
      {
        "id": "d1",
        "text": "migrate",
        "isDistractor": true
      },
      {
        "id": "d2",
        "text": "frontend",
        "isDistractor": true
      },
      {
        "id": "d3",
        "text": "deploys",
        "isDistractor": true
      }
    ],
    "translations": {
      "the": "el/la",
      "backend": "backend",
      "developer": "desarrollador",
      "migrates": "migra",
      "database": "base de datos",
      "to": "a",
      "a": "un/una",
      "new": "nuevo",
      "server": "servidor",
      "migrate": "migrar",
      "frontend": "frontend",
      "deploys": "despliega"
    },
    "metadata": {
      "tense": "present simple",
      "isNegative": false,
      "isQuestion": false,
      "difficulty": "beginner",
      "topic": "software engineering"
    }
  },
  {
    "hints": [
      "Sujeto: Lisa",
      "Verbo: render (mostrar/renderizar)",
      "Complemento: las interfaces de usuario en la pipeline"
    ],
    "hintDisplay": "Sujeto: Lisa / Verbo: render (mostrar/renderizar) / Complemento: las interfaces de usuario en la pipeline",
    "spanishSentence": "Lisa no renderiza las interfaces de usuario en la pipeline",
    "correctSentence": "Lisa does not render the user interfaces in the pipeline",
    "cards": [
      {
        "id": "c1",
        "text": "Lisa",
        "isDistractor": false
      },
      {
        "id": "c2",
        "text": "does",
        "isDistractor": false
      },
      {
        "id": "c3",
        "text": "not",
        "isDistractor": false
      },
      {
        "id": "c4",
        "text": "render",
        "isDistractor": false
      },
      {
        "id": "c5",
        "text": "the",
        "isDistractor": false
      },
      {
        "id": "c6",
        "text": "user",
        "isDistractor": false
      },
      {
        "id": "c7",
        "text": "interfaces",
        "isDistractor": false
      },
      {
        "id": "c8",
        "text": "in",
        "isDistractor": false
      },
      {
        "id": "c9",
        "text": "the",
        "isDistractor": false
      },
      {
        "id": "c10",
        "text": "pipeline",
        "isDistractor": false
      },
      {
        "id": "d1",
        "text": "renders",
        "isDistractor": true
      },
      {
        "id": "d2",
        "text": "at",
        "isDistractor": true
      },
      {
        "id": "d3",
        "text": "builds",
        "isDistractor": true
      }
    ],
    "translations": {
      "lisa": "Lisa",
      "does": "hace/do",
      "not": "no",
      "render": "renderizar",
      "the": "la/el/los/las",
      "user": "de usuario",
      "interfaces": "interfaces",
      "in": "en",
      "pipeline": "pipeline",
      "renders": "renderiza",
      "at": "en",
      "builds": "compila"
    },
    "metadata": {
      "tense": "present simple",
      "isNegative": true,
      "isQuestion": false,
      "difficulty": "beginner",
      "topic": "software engineering"
    }
  },
  {
    "hints": [
      "Sujeto: Daniel",
      "Verbo: evaluar",
      "Complemento: el código nuevo en el pull request"
    ],
    "hintDisplay": "Sujeto: Daniel / Verbo: evaluar / Complemento: el código nuevo en el pull request",
    "spanishSentence": "Daniel evalúa el código nuevo en el pull request",
    "correctSentence": "Daniel evaluates the new code in the pull request",
    "cards": [
      {
        "id": "c1",
        "text": "Daniel",
        "isDistractor": false
      },
      {
        "id": "c2",
        "text": "evaluates",
        "isDistractor": false
      },
      {
        "id": "c3",
        "text": "the",
        "isDistractor": false
      },
      {
        "id": "c4",
        "text": "new",
        "isDistractor": false
      },
      {
        "id": "c5",
        "text": "code",
        "isDistractor": false
      },
      {
        "id": "c6",
        "text": "in",
        "isDistractor": false
      },
      {
        "id": "c7",
        "text": "the",
        "isDistractor": false
      },
      {
        "id": "c8",
        "text": "pull",
        "isDistractor": false
      },
      {
        "id": "c9",
        "text": "request",
        "isDistractor": false
      },
      {
        "id": "d1",
        "text": "evaluating",
        "isDistractor": true
      },
      {
        "id": "d2",
        "text": "at",
        "isDistractor": true
      },
      {
        "id": "d3",
        "text": "old",
        "isDistractor": true
      }
    ],
    "translations": {
      "daniel": "Daniel",
      "evaluates": "evalúa",
      "the": "el/la",
      "new": "nuevo",
      "code": "código",
      "in": "en",
      "pull": "pull",
      "request": "request",
      "evaluating": "evaluando",
      "at": "en",
      "old": "viejo"
    },
    "metadata": {
      "tense": "present simple",
      "isNegative": false,
      "isQuestion": false,
      "difficulty": "beginner",
      "topic": "software engineering"
    }
  },
  {
    "hints": [
      "Sujeto: Pedro (un desarrollador de software)",
      "Verbo: build (construir)",
      "Complemento: aplicaciones móviles"
    ],
    "hintDisplay": "Sujeto: Pedro (un desarrollador de software) / Verbo: build (construir) / Complemento: aplicaciones móviles",
    "spanishSentence": "Pedro construye aplicaciones móviles.",
    "correctSentence": "Pedro builds mobile applications.",
    "cards": [
      {
        "id": "c1",
        "text": "Pedro",
        "isDistractor": false
      },
      {
        "id": "c2",
        "text": "builds",
        "isDistractor": false
      },
      {
        "id": "c3",
        "text": "mobile",
        "isDistractor": false
      },
      {
        "id": "c4",
        "text": "applications",
        "isDistractor": false
      },
      {
        "id": "d1",
        "text": "write",
        "isDistractor": true
      },
      {
        "id": "d2",
        "text": "desktop",
        "isDistractor": true
      },
      {
        "id": "d3",
        "text": "tests",
        "isDistractor": true
      }
    ],
    "translations": {
      "pedro": "Pedro",
      "builds": "construye",
      "mobile": "móviles",
      "applications": "aplicaciones",
      "write": "escribe",
      "desktop": "de escritorio",
      "tests": "pruebas"
    },
    "metadata": {
      "tense": "present simple",
      "isNegative": false,
      "isQuestion": false,
      "difficulty": "beginner",
      "topic": "software engineering"
    }
  },
  {
    "hints": [
      "Sujeto: Sofia",
      "Verbo: optimizar",
      "Complemento: el código del pipeline de CI",
      "Tiempo: cada día"
    ],
    "hintDisplay": "Sujeto: Sofia / Verbo: optimizar / Complemento: el código del pipeline de CI / Tiempo: cada día",
    "spanishSentence": "Sofia no optimiza el código del pipeline de CI cada día",
    "correctSentence": "Sofia doesn't optimize the CI pipeline code every day",
    "cards": [
      {
        "id": "c1",
        "text": "Sofia",
        "isDistractor": false
      },
      {
        "id": "c2",
        "text": "doesn't",
        "isDistractor": false
      },
      {
        "id": "c3",
        "text": "optimize",
        "isDistractor": false
      },
      {
        "id": "c4",
        "text": "the",
        "isDistractor": false
      },
      {
        "id": "c5",
        "text": "CI",
        "isDistractor": false
      },
      {
        "id": "c6",
        "text": "pipeline",
        "isDistractor": false
      },
      {
        "id": "c7",
        "text": "code",
        "isDistractor": false
      },
      {
        "id": "c8",
        "text": "every",
        "isDistractor": false
      },
      {
        "id": "c9",
        "text": "day",
        "isDistractor": false
      },
      {
        "id": "d1",
        "text": "don't",
        "isDistractor": true
      },
      {
        "id": "d2",
        "text": "optimizes",
        "isDistractor": true
      },
      {
        "id": "d3",
        "text": "performance",
        "isDistractor": true
      }
    ],
    "translations": {
      "sofia": "Sofia",
      "doesn't": "no",
      "optimize": "optimizar",
      "the": "el",
      "ci": "CI",
      "pipeline": "pipeline",
      "code": "código",
      "every": "cada",
      "day": "día",
      "don't": "no (error)",
      "optimizes": "optimiza (error)",
      "performance": "rendimiento"
    },
    "metadata": {
      "tense": "present simple",
      "isNegative": true,
      "isQuestion": false,
      "difficulty": "beginner",
      "topic": "software engineering"
    }
  },
  {
    "hints": [
      "Sujeto: Juan",
      "Verbo: compilar",
      "Complemento: el código cada mañana"
    ],
    "hintDisplay": "Sujeto: Juan / Verbo: compilar / Complemento: el código cada mañana",
    "spanishSentence": "Juan no compila el código cada mañana",
    "correctSentence": "Juan does not compile the code every morning",
    "cards": [
      {
        "id": "c1",
        "text": "Juan",
        "isDistractor": false
      },
      {
        "id": "c2",
        "text": "does",
        "isDistractor": false
      },
      {
        "id": "c3",
        "text": "not",
        "isDistractor": false
      },
      {
        "id": "c4",
        "text": "compile",
        "isDistractor": false
      },
      {
        "id": "c5",
        "text": "the",
        "isDistractor": false
      },
      {
        "id": "c6",
        "text": "code",
        "isDistractor": false
      },
      {
        "id": "c7",
        "text": "every",
        "isDistractor": false
      },
      {
        "id": "c8",
        "text": "morning",
        "isDistractor": false
      },
      {
        "id": "d1",
        "text": "compiles",
        "isDistractor": true
      },
      {
        "id": "d2",
        "text": "never",
        "isDistractor": true
      },
      {
        "id": "d3",
        "text": "software",
        "isDistractor": true
      }
    ],
    "translations": {
      "juan": "Juan",
      "does": "hace",
      "not": "no",
      "compile": "compilar",
      "the": "el",
      "code": "código",
      "every": "cada",
      "morning": "mañana",
      "compiles": "compila",
      "never": "nunca",
      "software": "software"
    },
    "metadata": {
      "tense": "present simple",
      "isNegative": true,
      "isQuestion": false,
      "difficulty": "beginner",
      "topic": "software engineering"
    }
  },
  {
    "hints": [
      "Sujeto: Julia",
      "Verbo: consultar (query)",
      "Complemento: la base de datos"
    ],
    "hintDisplay": "Sujeto: Julia / Verbo: consultar (query) / Complemento: la base de datos",
    "spanishSentence": "Julia consulta la base de datos diariamente",
    "correctSentence": "Julia queries the database daily",
    "cards": [
      {
        "id": "c1",
        "text": "Julia",
        "isDistractor": false
      },
      {
        "id": "c2",
        "text": "queries",
        "isDistractor": false
      },
      {
        "id": "c3",
        "text": "the",
        "isDistractor": false
      },
      {
        "id": "c4",
        "text": "database",
        "isDistractor": false
      },
      {
        "id": "c5",
        "text": "daily",
        "isDistractor": false
      },
      {
        "id": "d1",
        "text": "updates",
        "isDistractor": true
      },
      {
        "id": "d2",
        "text": "weekly",
        "isDistractor": true
      },
      {
        "id": "d3",
        "text": "server",
        "isDistractor": true
      }
    ],
    "translations": {
      "julia": "Julia",
      "queries": "consulta",
      "the": "la",
      "database": "base de datos",
      "daily": "diariamente",
      "updates": "actualiza",
      "weekly": "semanalmente",
      "server": "servidor"
    },
    "metadata": {
      "tense": "present simple",
      "isNegative": false,
      "isQuestion": false,
      "difficulty": "beginner",
      "topic": "software engineering"
    }
  },
  {
    "hints": [
      "Sujeto: el desarrollador de backend",
      "Verbo: query (consultar)",
      "Complemento: la base de datos"
    ],
    "hintDisplay": "Sujeto: el desarrollador de backend / Verbo: query (consultar) / Complemento: la base de datos",
    "spanishSentence": "El desarrollador de backend consulta la base de datos cada día",
    "correctSentence": "The backend developer queries the database every day",
    "cards": [
      {
        "id": "c1",
        "text": "The",
        "isDistractor": false
      },
      {
        "id": "c2",
        "text": "backend",
        "isDistractor": false
      },
      {
        "id": "c3",
        "text": "developer",
        "isDistractor": false
      },
      {
        "id": "c4",
        "text": "queries",
        "isDistractor": false
      },
      {
        "id": "c5",
        "text": "the",
        "isDistractor": false
      },
      {
        "id": "c6",
        "text": "database",
        "isDistractor": false
      },
      {
        "id": "c7",
        "text": "every",
        "isDistractor": false
      },
      {
        "id": "c8",
        "text": "day",
        "isDistractor": false
      },
      {
        "id": "d1",
        "text": "updates",
        "isDistractor": true
      },
      {
        "id": "d2",
        "text": "server",
        "isDistractor": true
      },
      {
        "id": "d3",
        "text": "each",
        "isDistractor": true
      }
    ],
    "translations": {
      "the": "el/la",
      "backend": "backend",
      "developer": "desarrollador",
      "queries": "consulta",
      "database": "base de datos",
      "every": "cada",
      "day": "día",
      "updates": "actualiza",
      "server": "servidor",
      "each": "cada"
    },
    "metadata": {
      "tense": "present simple",
      "isNegative": false,
      "isQuestion": false,
      "difficulty": "beginner",
      "topic": "software engineering"
    }
  },
  {
    "hints": [
      "Sujeto: Daniel",
      "Verbo: scale (escalar/ampliar)",
      "Complemento: la aplicación (la aplicación)"
    ],
    "hintDisplay": "Sujeto: Daniel / Verbo: scale (escalar/ampliar) / Complemento: la aplicación",
    "spanishSentence": "Daniel escala la aplicación cada día",
    "correctSentence": "Daniel scales the application every day",
    "cards": [
      {
        "id": "c1",
        "text": "Daniel",
        "isDistractor": false
      },
      {
        "id": "c2",
        "text": "scales",
        "isDistractor": false
      },
      {
        "id": "c3",
        "text": "the",
        "isDistractor": false
      },
      {
        "id": "c4",
        "text": "application",
        "isDistractor": false
      },
      {
        "id": "c5",
        "text": "every",
        "isDistractor": false
      },
      {
        "id": "c6",
        "text": "day",
        "isDistractor": false
      },
      {
        "id": "d1",
        "text": "scaled",
        "isDistractor": true
      },
      {
        "id": "d2",
        "text": "server",
        "isDistractor": true
      },
      {
        "id": "d3",
        "text": "week",
        "isDistractor": true
      }
    ],
    "translations": {
      "daniel": "Daniel",
      "scales": "escala",
      "the": "la",
      "application": "aplicación",
      "every": "cada",
      "day": "día",
      "scaled": "escalado",
      "server": "servidor",
      "week": "semana"
    },
    "metadata": {
      "tense": "present simple",
      "isNegative": false,
      "isQuestion": false,
      "difficulty": "beginner",
      "topic": "software engineering"
    }
  },
  {
    "hints": [
      "Sujeto: el desarrollador (the developer)",
      "Verbo: compilar (to compile)",
      "Complemento: el código (the code)"
    ],
    "hintDisplay": "Sujeto: el desarrollador / Verbo: compilar / Complemento: el código",
    "spanishSentence": "El desarrollador compila el código cada día",
    "correctSentence": "The developer compiles the code every day",
    "cards": [
      {
        "id": "c1",
        "text": "The",
        "isDistractor": false
      },
      {
        "id": "c2",
        "text": "developer",
        "isDistractor": false
      },
      {
        "id": "c3",
        "text": "compiles",
        "isDistractor": false
      },
      {
        "id": "c4",
        "text": "the",
        "isDistractor": false
      },
      {
        "id": "c5",
        "text": "code",
        "isDistractor": false
      },
      {
        "id": "c6",
        "text": "every",
        "isDistractor": false
      },
      {
        "id": "c7",
        "text": "day",
        "isDistractor": false
      },
      {
        "id": "d1",
        "text": "builds",
        "isDistractor": true
      },
      {
        "id": "d2",
        "text": "engineer",
        "isDistractor": true
      },
      {
        "id": "d3",
        "text": "program",
        "isDistractor": true
      }
    ],
    "translations": {
      "the": "el/la",
      "developer": "desarrollador",
      "compiles": "compila",
      "code": "código",
      "every": "cada",
      "day": "día",
      "builds": "construye",
      "engineer": "ingeniero",
      "program": "programa"
    },
    "metadata": {
      "tense": "present simple",
      "isNegative": false,
      "isQuestion": false,
      "difficulty": "beginner",
      "topic": "software engineering"
    }
  },
  {
    "hints": [
      "Sujeto: Juan",
      "Verbo: display (mostrar)",
      "Complemento: los errores en la pantalla"
    ],
    "hintDisplay": "Sujeto: Juan / Verbo: display (mostrar) / Complemento: los errores en la pantalla",
    "spanishSentence": "Juan muestra los errores en la pantalla.",
    "correctSentence": "Juan displays the errors on the screen.",
    "cards": [
      {
        "id": "c1",
        "text": "Juan",
        "isDistractor": false
      },
      {
        "id": "c2",
        "text": "displays",
        "isDistractor": false
      },
      {
        "id": "c3",
        "text": "the",
        "isDistractor": false
      },
      {
        "id": "c4",
        "text": "errors",
        "isDistractor": false
      },
      {
        "id": "c5",
        "text": "on",
        "isDistractor": false
      },
      {
        "id": "c6",
        "text": "the",
        "isDistractor": false
      },
      {
        "id": "c7",
        "text": "screen",
        "isDistractor": false
      },
      {
        "id": "d1",
        "text": "hides",
        "isDistractor": true
      },
      {
        "id": "d2",
        "text": "in",
        "isDistractor": true
      },
      {
        "id": "d3",
        "text": "warnings",
        "isDistractor": true
      }
    ],
    "translations": {
      "juan": "Juan",
      "displays": "muestra",
      "the": "el / la / los / las",
      "errors": "errores",
      "on": "en",
      "screen": "pantalla",
      "hides": "oculta",
      "in": "dentro",
      "warnings": "advertencias"
    },
    "metadata": {
      "tense": "present simple",
      "isNegative": false,
      "isQuestion": false,
      "difficulty": "beginner",
      "topic": "software engineering"
    }
  },
  {
    "hints": [
      "Sujeto: el architect",
      "Verbo: diseñar",
      "Complemento: la arquitectura del sistema"
    ],
    "hintDisplay": "Sujeto: el architect / Verbo: diseñar / Complemento: la arquitectura del sistema",
    "spanishSentence": "El architect diseña la arquitectura del sistema",
    "correctSentence": "The architect designs the system architecture",
    "cards": [
      {
        "id": "c1",
        "text": "The",
        "isDistractor": false
      },
      {
        "id": "c2",
        "text": "architect",
        "isDistractor": false
      },
      {
        "id": "c3",
        "text": "designs",
        "isDistractor": false
      },
      {
        "id": "c4",
        "text": "the",
        "isDistractor": false
      },
      {
        "id": "c5",
        "text": "system",
        "isDistractor": false
      },
      {
        "id": "c6",
        "text": "architecture",
        "isDistractor": false
      },
      {
        "id": "d1",
        "text": "develops",
        "isDistractor": true
      },
      {
        "id": "d2",
        "text": "code",
        "isDistractor": true
      },
      {
        "id": "d3",
        "text": "writes",
        "isDistractor": true
      }
    ],
    "translations": {
      "the": "el/la",
      "architect": "arquitecto",
      "designs": "diseña",
      "system": "sistema",
      "architecture": "arquitectura",
      "develops": "desarrolla",
      "code": "código",
      "writes": "escribe"
    },
    "metadata": {
      "tense": "present simple",
      "isNegative": false,
      "isQuestion": false,
      "difficulty": "beginner",
      "topic": "software engineering"
    }
  },
  {
    "hints": [
      "Sujeto: el ingeniero de DevOps",
      "Verbo: deploy (no hacer)",
      "Complemento: sin pruebas"
    ],
    "hintDisplay": "Sujeto: el ingeniero de DevOps / Verbo: deploy (no hacer) / Complemento: sin pruebas",
    "spanishSentence": "El ingeniero de DevOps no despliega sin pruebas",
    "correctSentence": "The DevOps engineer does not deploy without testing",
    "cards": [
      {
        "id": "c1",
        "text": "The",
        "isDistractor": false
      },
      {
        "id": "c2",
        "text": "DevOps",
        "isDistractor": false
      },
      {
        "id": "c3",
        "text": "engineer",
        "isDistractor": false
      },
      {
        "id": "c4",
        "text": "does",
        "isDistractor": false
      },
      {
        "id": "c5",
        "text": "not",
        "isDistractor": false
      },
      {
        "id": "c6",
        "text": "deploy",
        "isDistractor": false
      },
      {
        "id": "c7",
        "text": "without",
        "isDistractor": false
      },
      {
        "id": "c8",
        "text": "testing",
        "isDistractor": false
      },
      {
        "id": "d1",
        "text": "deploys",
        "isDistractor": true
      },
      {
        "id": "d2",
        "text": "before",
        "isDistractor": true
      },
      {
        "id": "d3",
        "text": "debugging",
        "isDistractor": true
      }
    ],
    "translations": {
      "the": "el",
      "devops": "DevOps",
      "engineer": "ingeniero",
      "does": "hace",
      "not": "no",
      "deploy": "desplegar",
      "without": "sin",
      "testing": "pruebas",
      "deploys": "despliega",
      "before": "antes",
      "debugging": "depuración"
    },
    "metadata": {
      "tense": "present simple",
      "isNegative": true,
      "isQuestion": false,
      "difficulty": "beginner",
      "topic": "software engineering"
    }
  },
  {
    "hints": [
      "Sujeto: el desarrollador frontend",
      "Verbo: estilizar (negación)",
      "Complemento: los componentes sin una guía de estilos"
    ],
    "hintDisplay": "Sujeto: el desarrollador frontend / Verbo: estilizar (negación) / Complemento: los componentes sin una guía de estilos",
    "spanishSentence": "El desarrollador frontend no estiliza los componentes sin una guía de estilos",
    "correctSentence": "The frontend developer does not style components without a style guide",
    "cards": [
      {
        "id": "c1",
        "text": "The",
        "isDistractor": false
      },
      {
        "id": "c2",
        "text": "frontend",
        "isDistractor": false
      },
      {
        "id": "c3",
        "text": "developer",
        "isDistractor": false
      },
      {
        "id": "c4",
        "text": "does",
        "isDistractor": false
      },
      {
        "id": "c5",
        "text": "not",
        "isDistractor": false
      },
      {
        "id": "c6",
        "text": "style",
        "isDistractor": false
      },
      {
        "id": "c7",
        "text": "components",
        "isDistractor": false
      },
      {
        "id": "c8",
        "text": "without",
        "isDistractor": false
      },
      {
        "id": "c9",
        "text": "a",
        "isDistractor": false
      },
      {
        "id": "c10",
        "text": "style",
        "isDistractor": false
      },
      {
        "id": "c11",
        "text": "guide",
        "isDistractor": false
      },
      {
        "id": "d1",
        "text": "never",
        "isDistractor": true
      },
      {
        "id": "d2",
        "text": "styles",
        "isDistractor": true
      },
      {
        "id": "d3",
        "text": "does",
        "isDistractor": true
      }
    ],
    "translations": {
      "the": "el",
      "frontend": "frontend",
      "developer": "desarrollador",
      "does": "hace",
      "not": "no",
      "style": "estilizar",
      "components": "componentes",
      "without": "sin",
      "a": "una",
      "guide": "guía",
      "never": "nunca",
      "styles": "estilos"
    },
    "metadata": {
      "tense": "present simple",
      "isNegative": true,
      "isQuestion": false,
      "difficulty": "beginner",
      "topic": "software engineering"
    }
  },
  {
    "hints": [
      "Sujeto: Julia",
      "Verbo: render (mostrar/renderizar)",
      "Complemento: componentes de UI en la pantalla"
    ],
    "hintDisplay": "Sujeto: Julia / Verbo: render (mostrar/renderizar) / Complemento: componentes de UI en la pantalla",
    "spanishSentence": "Julia renderiza componentes de UI en la pantalla",
    "correctSentence": "Julia renders UI components on screen",
    "cards": [
      {
        "id": "c1",
        "text": "Julia",
        "isDistractor": false
      },
      {
        "id": "c2",
        "text": "renders",
        "isDistractor": false
      },
      {
        "id": "c3",
        "text": "UI",
        "isDistractor": false
      },
      {
        "id": "c4",
        "text": "components",
        "isDistractor": false
      },
      {
        "id": "c5",
        "text": "on",
        "isDistractor": false
      },
      {
        "id": "c6",
        "text": "screen",
        "isDistractor": false
      },
      {
        "id": "d1",
        "text": "deploy",
        "isDistractor": true
      },
      {
        "id": "d2",
        "text": "compiled",
        "isDistractor": true
      },
      {
        "id": "d3",
        "text": "from",
        "isDistractor": true
      }
    ],
    "translations": {
      "julia": "Julia",
      "renders": "renderiza",
      "ui": "UI",
      "components": "componentes",
      "on": "en",
      "screen": "pantalla",
      "deploy": "implementa",
      "compiled": "compilado",
      "from": "desde"
    },
    "metadata": {
      "tense": "present simple",
      "isNegative": false,
      "isQuestion": false,
      "difficulty": "beginner",
      "topic": "software engineering"
    }
  },
  {
    "hints": [
      "Sujeto: El ingeniero de DevOps",
      "Verbo: deploy (desplegar)",
      "Complemento: la aplicación nueva al servidor de producción"
    ],
    "hintDisplay": "Sujeto: El ingeniero de DevOps / Verbo: deploy (desplegar) / Complemento: la aplicación nueva al servidor de producción",
    "spanishSentence": "El ingeniero de DevOps despliega la aplicación nueva al servidor de producción",
    "correctSentence": "The DevOps engineer deploys the new application to production",
    "cards": [
      {
        "id": "c1",
        "text": "The",
        "isDistractor": false
      },
      {
        "id": "c2",
        "text": "DevOps",
        "isDistractor": false
      },
      {
        "id": "c3",
        "text": "engineer",
        "isDistractor": false
      },
      {
        "id": "c4",
        "text": "deploys",
        "isDistractor": false
      },
      {
        "id": "c5",
        "text": "the",
        "isDistractor": false
      },
      {
        "id": "c6",
        "text": "new",
        "isDistractor": false
      },
      {
        "id": "c7",
        "text": "application",
        "isDistractor": false
      },
      {
        "id": "c8",
        "text": "to",
        "isDistractor": false
      },
      {
        "id": "c9",
        "text": "production",
        "isDistractor": false
      },
      {
        "id": "d1",
        "text": "deploy",
        "isDistractor": true
      },
      {
        "id": "d2",
        "text": "old",
        "isDistractor": true
      },
      {
        "id": "d3",
        "text": "development",
        "isDistractor": true
      }
    ],
    "translations": {
      "the": "el/la",
      "devops": "DevOps",
      "engineer": "ingeniero",
      "deploys": "despliega",
      "new": "nueva",
      "application": "aplicación",
      "to": "a",
      "production": "producción",
      "deploy": "desplegar",
      "old": "antigua",
      "development": "desarrollo"
    },
    "metadata": {
      "tense": "present simple",
      "isNegative": false,
      "isQuestion": false,
      "difficulty": "beginner",
      "topic": "software engineering"
    }
  },
  {
    "hints": [
      "Sujeto: el desarrollador",
      "Verbo: debug (depurar)",
      "Complemento: errores en el código"
    ],
    "hintDisplay": "Sujeto: el desarrollador / Verbo: debug (depurar) / Complemento: errores en el código",
    "spanishSentence": "El desarrollador depura errores en el código",
    "correctSentence": "The developer debugs errors in the code",
    "cards": [
      {
        "id": "c1",
        "text": "The",
        "isDistractor": false
      },
      {
        "id": "c2",
        "text": "developer",
        "isDistractor": false
      },
      {
        "id": "c3",
        "text": "debugs",
        "isDistractor": false
      },
      {
        "id": "c4",
        "text": "errors",
        "isDistractor": false
      },
      {
        "id": "c5",
        "text": "in",
        "isDistractor": false
      },
      {
        "id": "c6",
        "text": "the",
        "isDistractor": false
      },
      {
        "id": "c7",
        "text": "code",
        "isDistractor": false
      },
      {
        "id": "d1",
        "text": "fixes",
        "isDistractor": true
      },
      {
        "id": "d2",
        "text": "bugs",
        "isDistractor": true
      },
      {
        "id": "d3",
        "text": "at",
        "isDistractor": true
      }
    ],
    "translations": {
      "the": "el/la",
      "developer": "desarrollador",
      "debugs": "depura",
      "errors": "errores",
      "in": "en",
      "code": "código",
      "fixes": "arregla",
      "bugs": "bugs",
      "at": "en"
    },
    "metadata": {
      "tense": "present simple",
      "isNegative": false,
      "isQuestion": false,
      "difficulty": "beginner",
      "topic": "software engineering"
    }
  },
  {
    "hints": [
      "Sujeto: Lisa",
      "Verbo: documentar",
      "Complemento: el código"
    ],
    "hintDisplay": "Sujeto: Lisa / Verbo: documentar / Complemento: el código",
    "spanishSentence": "Lisa documenta el código diariamente",
    "correctSentence": "Lisa documents the code daily",
    "cards": [
      {
        "id": "c1",
        "text": "Lisa",
        "isDistractor": false
      },
      {
        "id": "c2",
        "text": "documents",
        "isDistractor": false
      },
      {
        "id": "c3",
        "text": "the",
        "isDistractor": false
      },
      {
        "id": "c4",
        "text": "code",
        "isDistractor": false
      },
      {
        "id": "c5",
        "text": "daily",
        "isDistractor": false
      },
      {
        "id": "d1",
        "text": "writes",
        "isDistractor": true
      },
      {
        "id": "d2",
        "text": "tests",
        "isDistractor": true
      },
      {
        "id": "d3",
        "text": "weekly",
        "isDistractor": true
      }
    ],
    "translations": {
      "lisa": "Lisa",
      "documents": "documenta",
      "the": "el",
      "code": "código",
      "daily": "diariamente",
      "writes": "escribe",
      "tests": "prueba",
      "weekly": "semanalmente"
    },
    "metadata": {
      "tense": "present simple",
      "isNegative": false,
      "isQuestion": false,
      "difficulty": "beginner",
      "topic": "software engineering"
    }
  }
]